{
  "schemaVersion": 1,
  "id": "graphix",
  "version": "${version}",

  "name": "GraphiX Mod",
  "description": "This mod will help you improve your server experience as it adds custom hd display, scordboards, and tab lists.",
  "authors": [
    "lochnessdragon"
  ],
  "contact": {
    "homepage": "https://fabricmc.net/",
    "sources": "https://github.com/lochnessdragon/FabricTestMod"
  },

  "license": "CC0-1.0",
  "icon": "assets/modid/icon.png",

  "environment": "server",
  "entrypoints": {
    "server": [
    	"com.github.lochnessdragon.GraphiXMod"
    ]
  },
  "mixins": [
    "graphix.mixins.json"
  ],

  "depends": {
    "fabricloader": ">=0.7.4",
    "fabric": "*",
    "minecraft": "1.16.x",
    "luckperms": "5.2.x"
  },
  "suggests": {
    "another-mod": "*"
  }
}
